climakitae/__init__.py
climakitae/_version.py
climakitae/core/__init__.py
climakitae/core/boundaries.py
climakitae/core/constants.py
climakitae/core/data_export.py
climakitae/core/data_interface.py
climakitae/core/data_load.py
climakitae/core/paths.py
climakitae/data/catalogs.csv
climakitae/data/gwl_1850-1900ref.csv
climakitae/data/gwl_1850-1900ref_timeidx.csv
climakitae/data/gwl_1981-2010ref.csv
climakitae/data/gwl_1981-2010ref_EC-Earth3_ssp370.csv
climakitae/data/gwl_1981-2010ref_timeidx.csv
climakitae/data/gwl_timing_table.csv
climakitae/data/hadisd_stations.csv
climakitae/data/tas_global_Historical.csv
climakitae/data/tas_global_SSP1_1_9.csv
climakitae/data/tas_global_SSP1_2_6.csv
climakitae/data/tas_global_SSP2_4_5.csv
climakitae/data/tas_global_SSP3_7_0.csv
climakitae/data/tas_global_SSP5_8_5.csv
climakitae/data/variable_descriptions.csv
climakitae/data/cached_tmy/tmy_future-minus-hist_rh_45km_CA_15degC.csv
climakitae/data/cached_tmy/tmy_future-minus-hist_rh_45km_CA_2degC.csv
climakitae/data/cached_tmy/tmy_future-minus-hist_rh_45km_CA_3degC.csv
climakitae/data/cached_tmy/tmy_future-minus-hist_rh_45km_losangeles_15degC.csv
climakitae/data/cached_tmy/tmy_future-minus-hist_rh_45km_losangeles_2degC.csv
climakitae/data/cached_tmy/tmy_future-minus-hist_rh_45km_losangeles_3degC.csv
climakitae/data/cached_tmy/tmy_future-minus-hist_rh_45km_santaclara_15degC.csv
climakitae/data/cached_tmy/tmy_future-minus-hist_rh_45km_santaclara_2degC.csv
climakitae/data/cached_tmy/tmy_future-minus-hist_rh_45km_santaclara_3degC.csv
climakitae/data/cached_tmy/tmy_future-minus-hist_temp_45km_CA_15degC.csv
climakitae/data/cached_tmy/tmy_future-minus-hist_temp_45km_CA_2degC.csv
climakitae/data/cached_tmy/tmy_future-minus-hist_temp_45km_CA_3degC.csv
climakitae/data/cached_tmy/tmy_future-minus-hist_temp_45km_losangeles_15degC.csv
climakitae/data/cached_tmy/tmy_future-minus-hist_temp_45km_losangeles_2degC.csv
climakitae/data/cached_tmy/tmy_future-minus-hist_temp_45km_losangeles_3degC.csv
climakitae-1.5.1.dist-info/licenses/LICENSE
climakitae-1.5.1.dist-info/METADATA
climakitae-1.5.1.dist-info/WHEEL
climakitae-1.5.1.dist-info/top_level.txt
climakitae-1.5.1.dist-info/RECORD
