Metadata-Version: 2.4
Name: climakitae
Version: 1.5.1
Summary: Climate data analysis toolkit
Author-email: Cal-Adapt Analytics Engine Team <analytics@cal-adapt.org>
License: BSD-3-Clause
Project-URL: Homepage, https://github.com/cal-adapt/climakitae
Project-URL: Documentation, https://climakitae.readthedocs.io
Project-URL: Repository, https://github.com/cal-adapt/climakitae
Project-URL: Issues, https://github.com/cal-adapt/climakitae/issues
Project-URL: Cal-Adapt, https://analytics.cal-adapt.org
Keywords: climate,data,analysis,california,cal-adapt
Classifier: Development Status :: 4 - Beta
Classifier: Programming Language :: Python :: 3
Classifier: Programming Language :: Python :: 3.12
Classifier: Programming Language :: Python :: 3.13
Classifier: License :: OSI Approved :: BSD License
Classifier: Operating System :: OS Independent
Classifier: Intended Audience :: Science/Research
Classifier: Topic :: Scientific/Engineering :: Atmospheric Science
Requires-Python: >=3.12
License-File: LICENSE
Requires-Dist: aiobotocore<=2.22.0
Requires-Dist: boto3<=1.37.3
Requires-Dist: dask
Requires-Dist: dask-gateway
Requires-Dist: dask-geopandas
Requires-Dist: fsspec
Requires-Dist: geopandas
Requires-Dist: geopy
Requires-Dist: intake
Requires-Dist: intake-esm<=2023.11.10
Requires-Dist: ipython
Requires-Dist: intake-geopandas
Requires-Dist: intake-xarray
Requires-Dist: matplotlib
Requires-Dist: numcodecs<=0.14.1
Requires-Dist: numpy
Requires-Dist: pandas
Requires-Dist: param
Requires-Dist: psutil
Requires-Dist: pyproj
Requires-Dist: pytz
Requires-Dist: rioxarray
Requires-Dist: s3fs
Requires-Dist: scipy
Requires-Dist: setuptools<81
Requires-Dist: shapely
Requires-Dist: statsmodels
Requires-Dist: timezonefinder
Requires-Dist: tqdm
Requires-Dist: xarray
Requires-Dist: xclim>0.56.0
Requires-Dist: xsdba
Requires-Dist: xmip
Provides-Extra: docs
Requires-Dist: Sphinx; extra == "docs"
Requires-Dist: sphinx-book-theme; extra == "docs"
Requires-Dist: sphinx-design; extra == "docs"
Requires-Dist: nbsphinx; extra == "docs"
Provides-Extra: dev
Requires-Dist: black; extra == "dev"
Requires-Dist: cftime; extra == "dev"
Requires-Dist: isort>=7.0.0; extra == "dev"
Requires-Dist: pytest; extra == "dev"
Requires-Dist: pytest-cov; extra == "dev"
Requires-Dist: pytest-xdist; extra == "dev"
Dynamic: license-file
